{"bg":"#1a1a2e","color":"","borderColor":"#ef5350","borderWidth":2,"borderRadius":6,"fontWeight":"","isSlot":false,"text":"","children":[{"bg":"","color":"#ef5350","borderColor":"","borderWidth":0,"borderRadius":0,"fontWeight":"bold","isSlot":false,"text":"","children":[],"tag":"span","classes":["delete-confirm-confirm-title","delete-confirm-title"],"x":10,"y":14,"w":170,"h":11,"textAlign":"center","translatableKey":"tsu.browse.delete_title"},{"bg":"","color":"#FFFFFF","borderColor":"","borderWidth":0,"borderRadius":0,"fontWeight":"","isSlot":false,"text":"preset name","children":[],"tag":"span","classes":["delete-confirm-row","delete-confirm-name"],"x":10,"y":32,"w":170,"h":11,"textAlign":"center"},{"bg":"","color":"#aaa","borderColor":"","borderWidth":0,"borderRadius":0,"fontWeight":"","isSlot":false,"text":"","children":[],"tag":"span","classes":["delete-confirm-row","delete-confirm-prompt"],"x":10,"y":46,"w":170,"h":11,"textAlign":"center","translatableKey":"tsu.browse.delete_prompt"},{"bg":"rgba(239,83,80,0.10)","color":"#ef5350","borderColor":"#ef5350","borderWidth":1,"borderRadius":3,"fontWeight":"","isSlot":false,"text":"","children":[],"tag":"div","classes":["delete-confirm-confirm-yes","delete-confirm-ok"],"x":24,"y":74,"w":69,"h":18,"textAlign":"center","hoverBg":"rgba(239,83,80,0.25)","hoverColor":"#fff","clickable":true,"translatableKey":"tsu.browse.delete_confirm_btn"},{"bg":"rgba(0,0,0,0.3)","color":"#aaa","borderColor":"#555","borderWidth":1,"borderRadius":3,"fontWeight":"","isSlot":false,"text":"","children":[],"tag":"div","classes":["delete-confirm-confirm-no","delete-confirm-cancel"],"x":103,"y":74,"w":63,"h":18,"textAlign":"center","hoverBg":"rgba(79,195,247,0.15)","hoverColor":"#fff","clickable":true,"translatableKey":"tsu.common.cancel"}],"tag":"div","classes":["dialog","confirm-popup","delete-confirm-confirm-popup"],"x":0,"y":0,"w":190,"h":102,"animationKey":"confirm-popup-open"}